./.gitignore
./.python-version
./LICENSE
./PKG-INFO
./README.md
./braille_canvas.py
./demo.py
./main.py
./pyproject.toml
ny2026-1.0.13.dist-info/METADATA
ny2026-1.0.13.dist-info/WHEEL
ny2026-1.0.13.dist-info/entry_points.txt
ny2026-1.0.13.dist-info/licenses/LICENSE
ny2026-1.0.13.dist-info/RECORD
