Metadata-Version: 2.4
Name: ny2026
Version: 1.0.13
Summary: A countdown to 2026 in your terminal
Project-URL: Homepage, https://github.com/willmcgugan/ny2026
Project-URL: Repository, https://github.com/willmcgugan/ny2026
Author-email: Will McGugan <willmcgugan@gmail.com>
License: MIT
License-File: LICENSE
Requires-Python: >=3.13
Requires-Dist: numpy>=2.4.0
Requires-Dist: rich>=14.2.0
Requires-Dist: sounddevice>=0.5.3
